gptio.py
gptio-0.1.7.dist-info/METADATA
gptio-0.1.7.dist-info/WHEEL
gptio-0.1.7.dist-info/top_level.txt
gptio-0.1.7.dist-info/RECORD
